akinyeleib/__init__.py
akinyeleib/github_scrape.py
github_scrape-0.3.4.dist-info/LICENSE
github_scrape-0.3.4.dist-info/METADATA
github_scrape-0.3.4.dist-info/WHEEL
github_scrape-0.3.4.dist-info/top_level.txt
github_scrape-0.3.4.dist-info/RECORD
