Metadata-Version: 2.1
Name: github-scrape
Version: 0.3.4
Summary: A program to scrape github followers
Author-email: Akinyele Ibrahim <iakinyele3@gmail.com>
Project-URL: Homepage, https://github.com/akinyeleib/github-followers-scrape
Keywords: Github,scrape,check followers
Classifier: Programming Language :: Python :: 3
Classifier: License :: OSI Approved :: MIT License
Classifier: Operating System :: OS Independent
Requires-Python: >=3.7
License-File: LICENSE
Requires-Dist: bs4
Requires-Dist: lxml
Requires-Dist: requests
